{"stats":{"total":2,"passed":2},"status":"passed","newTests":[{"id":"09b0f107212301225af3e93ef4d24932","name":"Test of the /player/:id endpoint","status":"passed","duration":332},{"id":"a4838f445326b17ae301180247eac7d7","name":"Test of the auth/login endpoint","status":"passed","duration":520}],"flakyTests":[],"retryTests":[],"name":"Allure Report","duration":852,"createdAt":1772305409843,"plugin":"Awesome","meta":{"reportId":"f9546fe1-846c-478a-9e38-1fc8e587330a","singleFile":false,"withTestResultsLinks":true},"pullRequestHref":"","jobHref":""}